[
    {
        "_id": "N43n6w",
        "title": "problem",
        "severity": 3,
        "description": "problem when problem",
        "createdAt": 1721560871898,
        "labels": "['critical']",
        "owner": {
            "fullname": "kinneret",
            "_id": "uE9GsS"
        }
    },
    {
        "_id": "phZPgO",
        "title": "flikring",
        "severity": 2,
        "description": "flikring all the time",
        "createdAt": 1721561045124,
        "labels": "['need-CR']",
        "owner": {
            "fullname": "kinneret",
            "_id": "uE9GsS"
        }
    },
    {
        "_id": "pDj9Vc",
        "title": "infinity load",
        "severity": 5,
        "description": "infinity load when scroll",
        "createdAt": 1721561143337,
        "labels": "['need-CR', 'dev-branch']",
        "owner": {
            "fullname": "kinneret",
            "_id": "uE9GsS"
        }
    }
]